swagchain/__init__.py
swagchain/aws/__init__.py
swagchain/aws/ml.py
swagchain/aws/odm.py
swagchain/aws/pubsub.py
swagchain/aws/store.py
swagchain/database/__init__.py
swagchain/database/embeddings.py
swagchain/database/vector.py
swagchain/language/__init__.py
swagchain/language/chat.py
swagchain/language/functions.py
swagchain/lib/__init__.py
swagchain/lib/client.py
swagchain/lib/utils.py
swagchain/tools/__init__.py
swagchain/tools/scrap.py
swagchain-0.0.23.dist-info/METADATA
swagchain-0.0.23.dist-info/WHEEL
swagchain-0.0.23.dist-info/RECORD
