Metadata-Version: 2.1
Name: swagchain
Version: 0.0.23
Summary: Swagchain is a python micro-framework to work with Large Language Models
Author: Oscar Bahamonde
Author-email: oscar.bahamonde.dev@gmail.com
Requires-Python: >=3.9,<4.0
Classifier: Programming Language :: Python :: 3
Classifier: Programming Language :: Python :: 3.9
Classifier: Programming Language :: Python :: 3.10
Classifier: Programming Language :: Python :: 3.11
Requires-Dist: boto3 (>=1.28.53,<2.0.0)
Requires-Dist: bs4 (>=0.0.1,<0.0.2)
Requires-Dist: click (>=8.1.7,<9.0.0)
Requires-Dist: jinja2 (>=3.1.2,<4.0.0)
Requires-Dist: langchain (>=0.0.301,<0.0.302)
Requires-Dist: lxml (>=4.9.3,<5.0.0)
Requires-Dist: numpy (>=1.25.2,<2.0.0)
Requires-Dist: openai (>=0.28.0,<0.29.0)
Requires-Dist: pydantic (==1.10.12)
Requires-Dist: rich (>=13.5.3,<14.0.0)
Requires-Dist: tiktoken (>=0.5.1,<0.6.0)
